chronulus_mcp/__init__.py
chronulus_mcp/__main__.py
chronulus_mcp/assets.py
chronulus_mcp/io.py
chronulus_mcp/session.py
chronulus_mcp/_assets/html/binary_predictor_analysis.html
chronulus_mcp/_assets/react/BetaPlot.jsx
chronulus_mcp/_assets/react/Scorecard.jsx
chronulus_mcp/agent/__init__.py
chronulus_mcp/agent/_types.py
chronulus_mcp/agent/forecaster.py
chronulus_mcp/agent/predictor.py
chronulus_mcp/stats/__init__.py
chronulus_mcp/stats/odds.py
chronulus_mcp_fastmcp-0.0.4.dist-info/METADATA
chronulus_mcp_fastmcp-0.0.4.dist-info/WHEEL
chronulus_mcp_fastmcp-0.0.4.dist-info/entry_points.txt
chronulus_mcp_fastmcp-0.0.4.dist-info/licenses/LICENSE
chronulus_mcp_fastmcp-0.0.4.dist-info/RECORD
