Metadata-Version: 2.4
Name: chronulus-mcp-fastmcp
Version: 0.0.4
Summary: An MCP Server for Chronulus AI Forecasting and Prediction Agents
Project-URL: Homepage, https://github.com/fastmcp-me/chronulus-mcp-ChronulusAI#readme
Project-URL: Repository, https://github.com/fastmcp-me/chronulus-mcp-ChronulusAI.git
Project-URL: Issues, https://github.com/fastmcp-me/chronulus-mcp-ChronulusAI/issues
Author-email: Chronulus AI <jeremy@chronulus.com>
License-File: LICENSE
Keywords: agents,forecasting,llm,mcp,prediction,timeseries
Classifier: License :: OSI Approved :: MIT License
Classifier: Programming Language :: Python :: 3
Classifier: Programming Language :: Python :: 3.10
Classifier: Programming Language :: Python :: 3.11
Classifier: Programming Language :: Python :: 3.12
Requires-Python: >=3.10
Requires-Dist: chronulus-core>=0.0.19
Requires-Dist: chronulus>=0.0.11
Requires-Dist: mcp[cli]>=1.3.0
Requires-Dist: pandas
Requires-Dist: requests
